<?xml version="1.0"?>
<page xmlns:xsi="http://www.w3.org/2001/XMLSchema-instance"
      layout="admin-2columns-left"
      xsi:noNamespaceSchemaLocation="urn:magento:framework:View/Layout/etc/page_configuration.xsd">
    <update handle="editor"/>
    <body>
        <referenceContainer name="left">
            <block class="NVT\MenuManagement\Block\Adminhtml\Menu\Edit\Tabs"
                   name="menumanager.menu.edit.tabs"/>
        </referenceContainer>
        <referenceContainer name="content">
            <block class="NVT\MenuManagement\Block\Adminhtml\Menu\Edit"
                   name="menumanager.menu.edit"/>
        </referenceContainer>
    </body>
</page>